[
    {
      "id": "f1",
      "type": "modbus-read",
      "z": "flow1",
      "name": "",
      "topic": "",
      "showStatusActivities": false,
      "showErrors": true,
      "unitid": "1",
      "dataType": "HoldingRegister",
      "adr": "0",
      "quantity": "5",
      "server": "c1",
      "useIOFile": false,
      "ioFile": "",
      "useIOForPayload": false,
      "x": 300,
      "y": 100,
      "wires": [["u1"]]
    },
    {
      "id": "u1",
      "type": "ui_template",
      "z": "flow1",
      "group": "g1",
      "name": "Registers",
      "order": 0,
      "width": "6",
      "height": "3",
      "format": "html",
      "storeOutMessages": true,
      "fwdInMessages": true,
      "template": "...",
      "x": 500,
      "y": 100,
      "wires": [["w1"]]
    },
    {
      "id": "w1",
      "type": "modbus-write",
      "z": "flow1",
      "name": "",
      "topic": "",
      "showStatusActivities": false,
      "showErrors": true,
      "unitid": "1",
      "dataType": "HoldingRegister",
      "adr": "0",
      "quantity": "1",
      "server": "c1",
      "useIOFile": false,
      "ioFile": "",
      "x": 700,
      "y": 100,
      "wires": []
    },
    {
      "id": "i1",
      "type": "inject",
      "z": "flow1",
      "name": "Trigger Read",
      "props": [{"p": "payload"}, {"p": "topic", "vt": "str"}],
      "repeat": "5",
      "crontab": "",
      "once": false,
      "onceDelay": 0.1,
      "topic": "",
      "payload": "",
      "payloadType": "date",
      "x": 100,
      "y": 100,
      "wires": [["f1"]]
    },
    {
      "id": "c1",
      "type": "modbus-client",
      "name": "Modbus Client",
      "clienttype": "tcp",
      "bufferCommands": true,
      "stateLogEnabled": false,
      "queueLogEnabled": false,
      "failureLogEnabled": true,
      "tcpHost": "127.0.0.1",
      "tcpPort": "5020",
      "unitId": 1
    },
    {
      "id": "g1",
      "type": "ui_group",
      "name": "Modbus Control",
      "tab": "t1",
      "order": 1,
      "disp": true,
      "width": "6"
    },
    {
      "id": "t1",
      "type": "ui_tab",
      "name": "Modbus",
      "icon": "dashboard",
      "order": 1
    }
  ]